uniswap_universal_router_decoder/__init__.py
uniswap_universal_router_decoder/_abi_builder.py
uniswap_universal_router_decoder/_constants.py
uniswap_universal_router_decoder/_decoder.py
uniswap_universal_router_decoder/_encoder.py
uniswap_universal_router_decoder/_enums.py
uniswap_universal_router_decoder/router_codec.py
uniswap_universal_router_decoder/utils.py
uniswap_universal_router_decoder-2.0.0.dist-info/LICENSE
uniswap_universal_router_decoder-2.0.0.dist-info/METADATA
uniswap_universal_router_decoder-2.0.0.dist-info/WHEEL
uniswap_universal_router_decoder-2.0.0.dist-info/top_level.txt
uniswap_universal_router_decoder-2.0.0.dist-info/RECORD
