Metadata-Version: 2.2
Name: uniswap-universal-router-decoder
Version: 2.0.0
Summary: Decode & Encode transactions sent to the Uniswap Universal Router. Support Uniswap V2, V3 & V4
Author-email: Elnaril <elnaril_dev@caramail.com>
License: MIT License
Project-URL: Homepage, https://github.com/Elnaril/uniswap-universal-router-decoder
Project-URL: Bug Tracker, https://github.com/Elnaril/uniswap-universal-router-decoder/issues
Project-URL: Discussions, https://github.com/Elnaril/uniswap-universal-router-decoder/discussions
Project-URL: Fiverr, https://www.fiverr.com/elnaril
Project-URL: Buy Me A Coffee, https://www.buymeacoffee.com/elnaril
Project-URL: Malt, https://www.malt.com/profile/elnaril
Project-URL: 𝕏, https://twitter.com/ElnarilDev
Keywords: blockchain,ethereum,unichain,uniswap,uniswap V4,exchange,dex,universal router,swap,decoder,encoder,codec,wrapper,SDK
Classifier: Development Status :: 5 - Production/Stable
Classifier: Intended Audience :: Developers
Classifier: License :: OSI Approved :: MIT License
Classifier: Natural Language :: English
Classifier: Programming Language :: Python :: 3
Classifier: Programming Language :: Python :: 3.9
Classifier: Programming Language :: Python :: 3.10
Classifier: Programming Language :: Python :: 3.11
Classifier: Programming Language :: Python :: 3.12
Classifier: Programming Language :: Python :: 3.13
Classifier: Operating System :: OS Independent
Requires-Python: >=3.9
License-File: LICENSE
Requires-Dist: web3<8.0.0,>=6.0.0
